Metadata-Version: 1.2
Name: notes-gen
Version: 0.0.8
Summary: A static site generator for markdown notes.
Home-page: https://github.com/sunitdeshpande/notes-gen
Author: Sunit Deshpande
Author-email: sunitdeshpande1234@gmail.com
License: WTFPL
Keywords: notes generator static site
Platform: UNKNOWN
Classifier: Development Status :: 3 - Alpha
Classifier: Intended Audience :: Developers
Classifier: Intended Audience :: Education
Classifier: Topic :: Education
Classifier: Topic :: Software Development :: Documentation
Classifier: Programming Language :: Python :: 2
Classifier: Programming Language :: Python :: 2.6
Classifier: Programming Language :: Python :: 2.7
Classifier: Programming Language :: Python :: 3
Classifier: Programming Language :: Python :: 3.2
Classifier: Programming Language :: Python :: 3.3
Classifier: Programming Language :: Python :: 3.4
Requires-Python: >=3
